setup.cfg
setup.py
cpp/src/quantize/bolt.cpp
pybolt.egg-info/PKG-INFO
pybolt.egg-info/SOURCES.txt
pybolt.egg-info/dependency_links.txt
pybolt.egg-info/not-zip-safe
pybolt.egg-info/requires.txt
pybolt.egg-info/top_level.txt
python/bolt/__init__.py
python/bolt/bolt.py
python/bolt/bolt_api.py
python/bolt/native.i