Metadata-Version: 1.1
Name: pybolt
Version: 0.1.4
Summary: Fast approximate matrix and vector operations
Home-page: https://github.com/dblalock/bolt
Author: Davis Blalock
Author-email: dblalock@mit.edu
License: MPL
Download-URL: https://github.com/dblalock/bolt/archive/0.1.tar.gz
Keywords: Machine Learning,Compression,Big Data
Platform: UNKNOWN
Classifier: Development Status :: 3 - Alpha
Classifier: Intended Audience :: Developers
Classifier: License :: OSI Approved :: Mozilla Public License 2.0 (MPL 2.0)
Classifier: Operating System :: Unix
Classifier: Operating System :: POSIX
Classifier: Programming Language :: C
Classifier: Programming Language :: C++
Classifier: Programming Language :: Python
Classifier: Programming Language :: Python :: 2.7
Classifier: Programming Language :: Python :: Implementation :: CPython
Classifier: Topic :: Scientific/Engineering :: Artificial Intelligence
Classifier: Topic :: Utilities
